java/encryption-app/build/distributions/encryption-app-1.0-SNAPSHOT/bin/encryption-app
java/encryption-app/build/distributions/encryption-app-1.0-SNAPSHOT/bin/encryption-app.bat
java/encryption-app/build/distributions/encryption-app-1.0-SNAPSHOT/lib/annotations-13.0.jar
java/encryption-app/build/distributions/encryption-app-1.0-SNAPSHOT/lib/bcprov-jdk15on-1.69.jar
java/encryption-app/build/distributions/encryption-app-1.0-SNAPSHOT/lib/encryption-app-1.0-SNAPSHOT.jar
java/encryption-app/build/distributions/encryption-app-1.0-SNAPSHOT/lib/jasypt-1.9.3.jar
java/encryption-app/build/distributions/encryption-app-1.0-SNAPSHOT/lib/kotlin-argparser-2.0.7.jar
java/encryption-app/build/distributions/encryption-app-1.0-SNAPSHOT/lib/kotlin-stdlib-1.9.0.jar
java/encryption-app/build/distributions/encryption-app-1.0-SNAPSHOT/lib/kotlin-stdlib-common-1.9.0.jar
java/encryption-app/build/distributions/encryption-app-1.0-SNAPSHOT/lib/kotlin-stdlib-jdk7-1.9.0.jar
java/encryption-app/build/distributions/encryption-app-1.0-SNAPSHOT/lib/kotlin-stdlib-jdk8-1.9.0.jar
java/encryption-app/build/distributions/encryption-app-1.0-SNAPSHOT/lib/py4j-0.10.9.7.jar
java/encryption-app/build/distributions/encryption-app-1.0-SNAPSHOT/lib/xenocom-0.0.7.jar
pysypt/__init__.py
pysypt/encryption.py
pysypt-1.0.4.dist-info/METADATA
pysypt-1.0.4.dist-info/WHEEL
pysypt-1.0.4.dist-info/top_level.txt
pysypt-1.0.4.dist-info/RECORD
