Metadata-Version: 2.1
Name: pysypt
Version: 1.0.4
Summary: Python wrapper around jasypt for encrypting and decrypting strings using the BouncyCastle Provider.
Requires-Python: >=3.11
Requires-Dist: py4j ~=0.10.9.7
Requires-Dist: pexpect ~=4.8.0
